[{"id":"56dab805b3c103ed","type":"tab","label":"Flow 5","disabled":false,"info":"","env":[]},{"id":"8ce4dba273861c72","type":"inject","z":"56dab805b3c103ed","name":"12:00 daily","props":[{"p":"payload"},{"p":"topic","vt":"str"}],"repeat":"","crontab":"00 12 * * *","once":false,"onceDelay":0.1,"topic":"","payload":"","payloadType":"date","x":150,"y":80,"wires":[["b9b3b6f99f8af0ce"]]},{"id":"330f29f285affea3","type":"debug","z":"56dab805b3c103ed","name":"debug","active":true,"tosidebar":true,"console":false,"tostatus":false,"complete":"payload","targetType":"msg","statusVal":"","statusType":"auto","x":1230,"y":80,"wires":[]},{"id":"0abac7c7efb52ced","type":"comment","z":"56dab805b3c103ed","name":"iBood.com - Headphone - vdbrink.github.io","info":"","x":230,"y":40,"wires":[]},{"id":"668ea8c3cb957eb7","type":"template","z":"56dab805b3c103ed","name":"ibood","field":"payload","fieldType":"msg","format":"html","syntax":"mustache","template":"In de aanbieding: koptelefoon bij iBood {{payload}}\nhttps://www.ibood.com/nl/s-be/o/1more-sonoflow-anc-bluetooth-koptelefoon-hc905/1045043","output":"str","x":910,"y":80,"wires":[["24bbf0ed705efa61"]]},{"id":"b9b3b6f99f8af0ce","type":"http request","z":"56dab805b3c103ed","name":"","method":"GET","ret":"txt","paytoqs":"ignore","url":"https://www.ibood.com/nl/s-be/o/1more-sonoflow-anc-bluetooth-koptelefoon-hc905/1045043","tls":"","persist":false,"proxy":"","insecureHTTPParser":false,"authType":"","senderr":false,"headers":[],"x":310,"y":80,"wires":[["19f8533b2bbd506f"]]},{"id":"19f8533b2bbd506f","type":"html","z":"56dab805b3c103ed","name":"","property":"payload","outproperty":"payload","tag":"._price_n1pwc_7","ret":"text","as":"single","x":490,"y":80,"wires":[["64cc088f1663e6c0"]]},{"id":"64cc088f1663e6c0","type":"change","z":"56dab805b3c103ed","name":"strip price","rules":[{"t":"set","p":"payload","pt":"msg","to":"$number(payload[0].$split(',')[0])","tot":"jsonata"}],"action":"","property":"","from":"","to":"","reg":false,"x":660,"y":80,"wires":[["5e78d1f465fe2268"]]},{"id":"5e78d1f465fe2268","type":"switch","z":"56dab805b3c103ed","name":"< 100","property":"payload","propertyType":"msg","rules":[{"t":"lt","v":"100","vt":"num"}],"checkall":"true","repair":false,"outputs":1,"x":790,"y":80,"wires":[["668ea8c3cb957eb7"]]},{"id":"24bbf0ed705efa61","type":"debug","z":"56dab805b3c103ed","name":"debug","active":true,"tosidebar":true,"console":false,"tostatus":false,"complete":"payload","targetType":"msg","statusVal":"","statusType":"auto","x":1030,"y":80,"wires":[]}]